visitoolkit_connector/__init__.py
visitoolkit_connector/connector.py
visitoolkit_connector-0.1.2.dist-info/METADATA
visitoolkit_connector-0.1.2.dist-info/RECORD
visitoolkit_connector-0.1.2.dist-info/WHEEL
visitoolkit_connector-0.1.2.dist-info/top_level.txt
