Metadata-Version: 2.1
Name: visitoolkit-connector
Version: 0.1.2
Summary: client implementation of "DMS JSON Data Exchange v1.4"
Home-page: https://github.com/stefanbraun-private/visitoolkit_connector
Author: Stefan Braun
Author-email: sbraun@datacomm.ch
License: GPL-3.0
Platform: UNKNOWN
Requires-Dist: visitoolkit-eventsystem (==0.1.5)
Requires-Dist: websocket-client-py3 (==0.15.0)
Requires-Dist: python-dateutil (==2.7.3)
